{
  "video_id": "Cgo-0UU848M",
  "title": "A free energy principle for generic quantum systems",
  "processing_started": "2025-06-09T09:05:52.216190",
  "transcript_downloaded": false,
  "transcript_error": "Exception during transcript download for Cgo-0UU848M: Command '['/home/trim/go/bin/fabric', '-y', 'https://www.youtube.com/watch?v=Cgo-0UU848M']' returned non-zero exit status 1.",
  "fabric_analyses_completed": false,
  "fabric_errors": [
    "Exception during summarize analysis for Cgo-0UU848M: Command '['/home/trim/go/bin/fabric', '--pattern', 'summarize']' returned non-zero exit status 1."
  ],
  "processing_failed": "2025-06-09T09:10:01.766506",
  "patterns_completed": [],
  "patterns_skipped": [],
  "fabric_analysis_finished": "2025-06-09T12:59:10.543990"
}